w3htmlmaker/__init__.py
w3htmlmaker/core.py
w3htmlmaker_math_s-0.0.4.dist-info/LICENSE.txt
w3htmlmaker_math_s-0.0.4.dist-info/METADATA
w3htmlmaker_math_s-0.0.4.dist-info/WHEEL
w3htmlmaker_math_s-0.0.4.dist-info/top_level.txt
w3htmlmaker_math_s-0.0.4.dist-info/RECORD
