Metadata-Version: 2.1
Name: w3htmlmaker-math-s
Version: 0.0.4
Summary: A HTML creator for articles
Home-page: https://github.com/math-s/w3htmlmaker
Author: Matheus Silva
Author-email: matheus.andrade1996@gmail.com
License: UNKNOWN
Platform: UNKNOWN
Classifier: Programming Language :: Python :: 3
Classifier: License :: OSI Approved :: MIT License
Classifier: Operating System :: OS Independent
Requires-Python: >=3.6
